contact_forms/__init__.py
contact_forms/admin.py
contact_forms/apps.py
contact_forms/forms.py
contact_forms/models.py
contact_forms/tests.py
contact_forms/urls.py
contact_forms/views.py
contact_forms/templates/contact/contact.html
contactforms/__init__.py
contactforms/admin.py
contactforms/apps.py
contactforms/forms.py
contactforms/models.py
contactforms/tests.py
contactforms/urls.py
contactforms/views.py
contactforms/migrations/0001_initial.py
contactforms/migrations/__init__.py
contactus/__init__.py
contactus/admin.py
contactus/apps.py
contactus/forms.py
contactus/models.py
contactus/tests.py
contactus/urls.py
contactus/views.py
django_contactforms-2.0.data/scripts/django-contactforms
django_contactforms-2.0.dist-info/LICENSE
django_contactforms-2.0.dist-info/METADATA
django_contactforms-2.0.dist-info/WHEEL
django_contactforms-2.0.dist-info/top_level.txt
django_contactforms-2.0.dist-info/RECORD
