Metadata-Version: 2.1
Name: django-contactforms
Version: 2.0
Summary: Django Contact Form Package
Home-page: https://github.com/sajib1066/django-contactforms
Author: Sajib Hossain
Author-email: sajib1066@gmail.com
License: UNKNOWN
Platform: UNKNOWN
Classifier: Framework :: Django
Classifier: Programming Language :: Python :: 3
Classifier: License :: OSI Approved :: MIT License
Classifier: Operating System :: OS Independent
